hoops/__init__.py
hoops/__version__.py
hoops/cli.py
hoops-0.1.0.dist-info/DESCRIPTION.rst
hoops-0.1.0.dist-info/METADATA
hoops-0.1.0.dist-info/RECORD
hoops-0.1.0.dist-info/WHEEL
hoops-0.1.0.dist-info/entry_points.txt
hoops-0.1.0.dist-info/metadata.json
hoops-0.1.0.dist-info/top_level.txt
