Metadata-Version: 2.0
Name: hoops
Version: 0.1.0
Summary: Hoops, The NBA cli
Home-page: https://github.com/Germione/hoops
Author: Jerome Pradier
Author-email: jerome.pradier@gmail.com
License: MIT
Keywords: packaging setuptools development
Platform: UNKNOWN
Classifier: Development Status :: 4 - Beta
Classifier: Intended Audience :: Developers
Classifier: Topic :: Software Development :: Build Tools
Classifier: License :: OSI Approved :: MIT License
Classifier: Programming Language :: Python :: 2
Classifier: Programming Language :: Python :: 2.7
Classifier: Programming Language :: Python :: 3
Classifier: Programming Language :: Python :: 3.6
Requires-Dist: twine
Requires-Dist: keyring
Requires-Dist: requests
